icevision/__init__.py
icevision/all.py
icevision/imports.py
icevision/soft_dependencies.py
icevision/backbones/__init__.py
icevision/backbones/backbone_config.py
icevision/backbones/mobilenet.py
icevision/backbones/resnest_fpn.py
icevision/backbones/resnet.py
icevision/backbones/resnet_fpn.py
icevision/backbones/resnet_fpn_utils.py
icevision/backbones/vgg.py
icevision/core/__init__.py
icevision/core/bbox.py
icevision/core/class_map.py
icevision/core/exceptions.py
icevision/core/id_map.py
icevision/core/keypoints.py
icevision/core/mask.py
icevision/core/record.py
icevision/core/record_components.py
icevision/core/record_defaults.py
icevision/core/record_type.py
icevision/core/record_utils.py
icevision/core/tasks.py
icevision/core/components/__init__.py
icevision/core/components/composite.py
icevision/data/__init__.py
icevision/data/convert_records_to_coco_style.py
icevision/data/convert_records_to_fo.py
icevision/data/data_splitter.py
icevision/data/dataset.py
icevision/data/prediction.py
icevision/data/record_collection.py
icevision/engines/__init__.py
icevision/engines/fastai/__init__.py
icevision/engines/fastai/imports.py
icevision/engines/fastai/adapters/__init__.py
icevision/engines/fastai/adapters/convert_dataloader_to_fastai.py
icevision/engines/fastai/adapters/fastai_metric_adapter.py
icevision/engines/fastai/learner/__init__.py
icevision/engines/fastai/learner/adapted_fastai_learner.py
icevision/engines/lightning/__init__.py
icevision/engines/lightning/imports.py
icevision/engines/lightning/lightning_model_adapter.py
icevision/metrics/__init__.py
icevision/metrics/metric.py
icevision/metrics/coco_metric/__init__.py
icevision/metrics/coco_metric/coco_metric.py
icevision/metrics/confusion_matrix/__init__.py
icevision/metrics/confusion_matrix/confusion_matrix.py
icevision/metrics/confusion_matrix/confusion_matrix_utils.py
icevision/models/__init__.py
icevision/models/base_show_results.py
icevision/models/checkpoint.py
icevision/models/inference.py
icevision-0.12.0.dist-info/LICENSE
icevision-0.12.0.dist-info/METADATA
icevision-0.12.0.dist-info/WHEEL
icevision-0.12.0.dist-info/top_level.txt
icevision-0.12.0.dist-info/RECORD
