Metadata-Version: 2.1
Name: icevision
Version: 0.12.0
Summary: Agnostic Computer Vision Framework
Author: Lucas Goulart Vazquez, Farid Hassainia
Author-email: lgvaz42@gmail.com, ai.fast.track.farid@gmail.com
License: Apache-2.0
Keywords: object detection,machine learning
Platform: UNKNOWN
Classifier: Development Status :: 4 - Beta
Classifier: Intended Audience :: Developers
Classifier: Programming Language :: Python :: 3.7
Classifier: Programming Language :: Python :: 3.8
Classifier: Topic :: Scientific/Engineering :: Artificial Intelligence
Classifier: Topic :: Scientific/Engineering :: Image Recognition
Requires-Python: <4,>=3.7
License-File: LICENSE
Requires-Dist: pillow (<9,>8.0.0)
Requires-Dist: torch (<1.11,>=1.9.0)
Requires-Dist: torchvision (<0.12,>=0.10.0)
Requires-Dist: fastcore (<1.4,>=1.3.0)
Requires-Dist: tqdm (<5,>=4.49.0)
Requires-Dist: opencv-python (<5,>=4.1.1)
Requires-Dist: albumentations (<1.1,>=1.0.3)
Requires-Dist: resnest (<0.0.7,>=0.0.6b20201125)
Requires-Dist: effdet (<0.3,>=0.2.1)
Requires-Dist: sahi (<1.0,>=0.8.19)
Requires-Dist: yolov5-icevision (>=6.0.0)
Requires-Dist: ipykernel (<6,>=4.10.1)
Requires-Dist: dataclasses (==0.6)
Requires-Dist: loguru (>=0.5.3)
Requires-Dist: importlib-metadata (>=1) ; python_version < "3.8"
Provides-Extra: all
Requires-Dist: fastai (<2.6,>=2.5.2) ; extra == 'all'
Requires-Dist: pytorch-lightning (>=1.4.5) ; extra == 'all'
Requires-Dist: wandb (>=0.10.7) ; extra == 'all'
Provides-Extra: dev
Requires-Dist: icevision[all] ; extra == 'dev'
Requires-Dist: keras-autodoc (==0.6.0) ; extra == 'dev'
Requires-Dist: black (==20.8b1) ; extra == 'dev'
Requires-Dist: pytest (<7,>=6) ; extra == 'dev'
Requires-Dist: mkdocs (<2,>=1.1.2) ; extra == 'dev'
Requires-Dist: mkdocs-material (<8,>=7.3.1) ; extra == 'dev'
Requires-Dist: mike (>=1.0) ; extra == 'dev'
Requires-Dist: jupyter (<2,>=1.0.0) ; extra == 'dev'
Requires-Dist: Sphinx (<4,>=3.1.0) ; extra == 'dev'
Requires-Dist: pytest-cov (<3,>=2.10.1) ; extra == 'dev'
Requires-Dist: flake8 (<4,>=3.8.3) ; extra == 'dev'
Requires-Dist: pre-commit (<3,>=2.8.2) ; extra == 'dev'
Requires-Dist: pytest-mock (>=3.6.1) ; extra == 'dev'
Provides-Extra: inference
Requires-Dist: icevision ; extra == 'inference'
